IRWPy/__init__.py
IRWPy-0.0.4.dist-info/LICENSE.txt
IRWPy-0.0.4.dist-info/METADATA
IRWPy-0.0.4.dist-info/WHEEL
IRWPy-0.0.4.dist-info/top_level.txt
IRWPy-0.0.4.dist-info/RECORD
