Metadata-Version: 2.1
Name: IRWPy
Version: 0.0.4
Summary: Inverse Radius Weighting Interpolation
Author-email: Bahnam Sadeghi <z5218858@zmail.unsw.edu.au>, Ahmed Eleish <ahmedmorad@gmail.com>
Classifier: Programming Language :: Python :: 3
Classifier: License :: OSI Approved :: MIT License
Classifier: Operating System :: OS Independent
Classifier: Intended Audience :: Science/Research
Requires-Python: >=3.11
License-File: LICENSE.txt
